[{"year":2014,"stock_number":42224474,"auction_in_progress":false,"images":["https://s3-us-west-1.amazonaws.com/vehimg/61355/42224474-1L.jpg","https://s3-us-west-1.amazonaws.com/vehimg/61355/42224474-2L.jpg","https://s3-us-west-1.amazonaws.com/vehimg/61355/42224474-3L.jpg","https://s3-us-west-1.amazonaws.com/vehimg/61355/42224474-4L.jpg","https://s3-us-west-1.amazonaws.com/vehimg/61355/42224474-5L.jpg","https://s3-us-west-1.amazonaws.com/vehimg/61355/42224474-6L.jpg","https://s3-us-west-1.amazonaws.com/vehimg/61355/42224474-7L.jpg","https://s3-us-west-1.amazonaws.com/vehimg/61355/42224474-8L.jpg","https://s3-us-west-1.amazonaws.com/vehimg/61355/42224474-9L.jpg","https://s3-us-west-1.amazonaws.com/vehimg/61355/42224474-10L.jpg","https://s3-us-west-1.amazonaws.com/vehimg/61355/42224474-11L.jpg","https://s3-us-west-1.amazonaws.com/vehimg/61355/42224474-12L.jpg","https://s3-us-west-1.amazonaws.com/vehimg/61355/42224474-13L.jpg","https://s3-us-west-1.amazonaws.com/vehimg/61355/42224474-14L.jpg","https://s3-us-west-1.amazonaws.com/vehimg/61355/42224474-15L.jpg","https://s3-us-west-1.amazonaws.com/vehimg/61355/42224474-16L.jpg"],"vehicle_name":"2014 HONDA CIVIC LX","odometer_value":76418,"odometer_type":"mi","odometer_status":"ACTUAL","location_city":"CULPEPER","location_state":"VA","location_zip":"22701","location_address":"15201 REVIEW RD","damage":"REAR","color":"Gray","interior_color":"","auction_verification":"Run & Drive Verified","start_code":"Run & Drive","vin":"2HGFB2F58EH500186","already_sold":false,"buy_it_now":3750,"retail_value":12923,"repair_cost":10079,"body_style":"SEDAN","current_bid_value":0,"currency":"USD","download_all_auction_pictures_url":"/rest-api/v2/lots/42224474/download-all-auction-pictures","show_clearvin_badge":true,"title_brand":"BRANDED IF REBUILT","vin_manufactured_country":"","vin_body":"Sedan","vin_vehicle_class":"","vin_model":"CIVIC","vin_series":"LX","vin_engine":"1.8L I-4 VVT, 143HP","vin_fuel_type":"Other","vin_cylinder":"","vin_restraint_system":"","vin_transmission":"Unknown","vin_drive_line_type":"Front Wheel Drive","loss_type":"Collision","primary_damage":"Rear","secondary_damage":"Front End","key_status":"Y","airbags":"INTACT","vehicle_wheels":null,"shrink_wrap":false,"videos":[{"url":"https://mediastorageaccountprod.blob.core.windows.net/media/42716469_VES-100_1","title":"Engine Video"}]},{"year":2014,"stock_number":41515501,"auction_in_progress":false,"images":["https://s3-us-west-1.amazonaws.com/vehimg/33812/41515501-1L.jpg","https://s3-us-west-1.amazonaws.com/vehimg/33812/41515501-2L.jpg","https://s3-us-west-1.amazonaws.com/vehimg/33812/41515501-3L.jpg","https://s3-us-west-1.amazonaws.com/vehimg/33812/41515501-4L.jpg","https://s3-us-west-1.amazonaws.com/vehimg/33812/41515501-5L.jpg","https://s3-us-west-1.amazonaws.com/vehimg/33812/41515501-6L.jpg","https://s3-us-west-1.amazonaws.com/vehimg/33812/41515501-7L.jpg","https://s3-us-west-1.amazonaws.com/vehimg/33812/41515501-8L.jpg","https://s3-us-west-1.amazonaws.com/vehimg/33812/41515501-9L.jpg","https://s3-us-west-1.amazonaws.com/vehimg/33812/41515501-10L.jpg","https://s3-us-west-1.amazonaws.com/vehimg/33812/41515501-11L.jpg","https://s3-us-west-1.amazonaws.com/vehimg/33812/41515501-12L.jpg","https://s3-us-west-1.amazonaws.com/vehimg/33812/41515501-13L.jpg","https://s3-us-west-1.amazonaws.com/vehimg/33812/41515501-14L.jpg","https://s3-us-west-1.amazonaws.com/vehimg/33812/41515501-15L.jpg","https://s3-us-west-1.amazonaws.com/vehimg/33812/41515501-16L.jpg"],"vehicle_name":"2014 FORD F-150 STX","odometer_value":211415,"odometer_type":"mi","odometer_status":"ACTUAL","location_city":"ACWORTH","location_state":"GA","location_zip":"30101","location_address":"6242 BLACKACRE TRAIL","damage":"FRONT END","color":"White","interior_color":"","auction_verification":"Run & Drive Verified","start_code":"Run & Drive","vin":"1FTFW1EF2EFB93610","already_sold":false,"buy_it_now":3700,"retail_value":14899,"repair_cost":14899,"body_style":"CREW CAB","current_bid_value":0,"currency":"USD","download_all_auction_pictures_url":"/rest-api/v2/lots/41515501/download-all-auction-pictures","show_clearvin_badge":true,"title_brand":"PARTS ONLY","vin_manufactured_country":"","vin_body":"Crew Cab","vin_vehicle_class":"","vin_model":"F150","vin_series":"STX","vin_engine":"5.0L V-8 DOHC, VVT, 360HP","vin_fuel_type":"Other","vin_cylinder":"","vin_restraint_system":"","vin_transmission":"Unknown","vin_drive_line_type":"Four Wheel Drive","loss_type":"Collision","primary_damage":"Front End","secondary_damage":"Right Side","key_status":"Y","airbags":"INTACT","vehicle_wheels":null,"shrink_wrap":false,"videos":[{"url":"https://mediastorageaccountprod.blob.core.windows.net/media/42006169_VES-100_1","title":"Engine Video"}]},{"year":2013,"stock_number":42240749,"auction_in_progress":false,"images":["https://s3-us-west-1.amazonaws.com/vehimg/19363/42240749-1L.jpg","https://s3-us-west-1.amazonaws.com/vehimg/19363/42240749-2L.jpg","https://s3-us-west-1.amazonaws.com/vehimg/19363/42240749-3L.jpg","https://s3-us-west-1.amazonaws.com/vehimg/19363/42240749-4L.jpg","https://s3-us-west-1.amazonaws.com/vehimg/19363/42240749-5L.jpg","https://s3-us-west-1.amazonaws.com/vehimg/19363/42240749-6L.jpg","https://s3-us-west-1.amazonaws.com/vehimg/19363/42240749-7L.jpg","https://s3-us-west-1.amazonaws.com/vehimg/19363/42240749-8L.jpg","https://s3-us-west-1.amazonaws.com/vehimg/19363/42240749-9L.jpg","https://s3-us-west-1.amazonaws.com/vehimg/19363/42240749-10L.jpg","https://s3-us-west-1.amazonaws.com/vehimg/19363/42240749-11L.jpg","https://s3-us-west-1.amazonaws.com/vehimg/19363/42240749-12L.jpg","https://s3-us-west-1.amazonaws.com/vehimg/19363/42240749-13L.jpg","https://s3-us-west-1.amazonaws.com/vehimg/19363/42240749-14L.jpg","https://s3-us-west-1.amazonaws.com/vehimg/19363/42240749-15L.jpg","https://s3-us-west-1.amazonaws.com/vehimg/19363/42240749-16L.jpg"],"vehicle_name":"2013 VOLKSWAGEN JETTA 2.0L S","odometer_value":93472,"odometer_type":"mi","odometer_status":"NOT ACTUAL","location_city":"EAST TAUNTON","location_state":"MA","location_zip":"02718","location_address":"580 MYRICKS STREET","damage":"FRONT END","color":"Black","interior_color":"","auction_verification":"Run & Drive Verified","start_code":"Run & Drive","vin":"3VW2K7AJ9DM280634","already_sold":false,"buy_it_now":null,"retail_value":8009,"repair_cost":9961,"body_style":"SEDAN","current_bid_value":0,"currency":"USD","download_all_auction_pictures_url":"/rest-api/v2/lots/42240749/download-all-auction-pictures","show_clearvin_badge":true,"title_brand":"PARTS ONLY","vin_manufactured_country":"","vin_body":"Sedan","vin_vehicle_class":"","vin_model":"JETTA","vin_series":"2.0L S","vin_engine":"2.0L I-4 115HP                                                                                                                                                                                          ","vin_fuel_type":"Other","vin_cylinder":"","vin_restraint_system":"","vin_transmission":"Unknown","vin_drive_line_type":"Front Wheel Drive","loss_type":"Collision","primary_damage":"Front End","secondary_damage":"","key_status":"Y","airbags":"DEPLOYED","vehicle_wheels":null,"shrink_wrap":false,"videos":[{"url":"https://mediastorageaccountprod.blob.core.windows.net/media/42732802_VES-100_1","title":"Engine Video"}]},{"year":2012,"stock_number":42540536,"auction_in_progress":false,"images":["https://s3-us-west-1.amazonaws.com/vehimg/29877/42540536-1L.jpg","https://s3-us-west-1.amazonaws.com/vehimg/29877/42540536-2L.jpg","https://s3-us-west-1.amazonaws.com/vehimg/29877/42540536-3L.jpg","https://s3-us-west-1.amazonaws.com/vehimg/29877/42540536-4L.jpg","https://s3-us-west-1.amazonaws.com/vehimg/29877/42540536-5L.jpg","https://s3-us-west-1.amazonaws.com/vehimg/29877/42540536-6L.jpg","https://s3-us-west-1.amazonaws.com/vehimg/29877/42540536-7L.jpg","https://s3-us-west-1.amazonaws.com/vehimg/29877/42540536-8L.jpg","https://s3-us-west-1.amazonaws.com/vehimg/29877/42540536-9L.jpg","https://s3-us-west-1.amazonaws.com/vehimg/29877/42540536-10L.jpg","https://s3-us-west-1.amazonaws.com/vehimg/29877/42540536-11L.jpg","https://s3-us-west-1.amazonaws.com/vehimg/29877/42540536-12L.jpg","https://s3-us-west-1.amazonaws.com/vehimg/29877/42540536-13L.jpg","https://s3-us-west-1.amazonaws.com/vehimg/29877/42540536-14L.jpg","https://s3-us-west-1.amazonaws.com/vehimg/29877/42540536-15L.jpg","https://s3-us-west-1.amazonaws.com/vehimg/29877/42540536-16L.jpg"],"vehicle_name":"2012 AUDI A8 4.2","odometer_value":163562,"odometer_type":"mi","odometer_status":"ACTUAL","location_city":"SOUTH BEND","location_state":"IN","location_zip":"46619","location_address":"3202 W SAMPLE ST","damage":"ENGINE DAMAGE","color":"Gray","interior_color":"","auction_verification":"Run & Drive Verified","start_code":"Run & Drive","vin":"WAUAVAFDXCN005748","already_sold":false,"buy_it_now":2000,"retail_value":4100,"repair_cost":null,"body_style":"SEDAN","current_bid_value":0,"currency":"USD","download_all_auction_pictures_url":"/rest-api/v2/lots/42540536/download-all-auction-pictures","show_clearvin_badge":true,"title_brand":"","vin_manufactured_country":"","vin_body":"Sedan","vin_vehicle_class":"","vin_model":"A8","vin_series":"4.2","vin_engine":"4.2L V-8 DI, DOHC, VVT, 372HP","vin_fuel_type":"Gasoline","vin_cylinder":"8 Cyl","vin_restraint_system":"Front Impact Airbag Driver;front Side Impact Airbag Driver;overhead Airbags;front Impact A","vin_transmission":"Automatic","vin_drive_line_type":"All Wheel Drive","loss_type":"Other","primary_damage":"Engine Damage","secondary_damage":"Right Front","key_status":"Y","airbags":"INTACT","vehicle_wheels":null,"shrink_wrap":false,"videos":[{"url":"https://mediastorageaccountprod.blob.core.windows.net/media/43033366_VES-100_1","title":"Engine Video"}]},{"year":2013,"stock_number":41980903,"auction_in_progress":false,"images":["https://s3-us-west-1.amazonaws.com/vehimg/16705/41980903-1L.jpg","https://s3-us-west-1.amazonaws.com/vehimg/16705/41980903-2L.jpg","https://s3-us-west-1.amazonaws.com/vehimg/16705/41980903-3L.jpg","https://s3-us-west-1.amazonaws.com/vehimg/16705/41980903-4L.jpg","https://s3-us-west-1.amazonaws.com/vehimg/16705/41980903-5L.jpg","https://s3-us-west-1.amazonaws.com/vehimg/16705/41980903-6L.jpg","https://s3-us-west-1.amazonaws.com/vehimg/16705/41980903-7L.jpg","https://s3-us-west-1.amazonaws.com/vehimg/16705/41980903-8L.jpg","https://s3-us-west-1.amazonaws.com/vehimg/16705/41980903-9L.jpg","https://s3-us-west-1.amazonaws.com/vehimg/16705/41980903-10L.jpg","https://s3-us-west-1.amazonaws.com/vehimg/16705/41980903-11L.jpg"],"vehicle_name":"2013 NISSAN JUKE SL","odometer_value":152944,"odometer_type":"mi","odometer_status":"ACTUAL","location_city":"CULPEPER","location_state":"VA","location_zip":"22701","location_address":"15201 REVIEW RD","damage":"NORMAL WEAR & TEAR","color":"White","interior_color":"","auction_verification":"Run & Drive Verified","start_code":"Run & Drive","vin":"JN8AF5MR6DT209604","already_sold":false,"buy_it_now":1000,"retail_value":2625,"repair_cost":null,"body_style":"UTILITY","current_bid_value":0,"currency":"USD","download_all_auction_pictures_url":"/rest-api/v2/lots/41980903/download-all-auction-pictures","show_clearvin_badge":false,"title_brand":"","vin_manufactured_country":"","vin_body":"Utility","vin_vehicle_class":"","vin_model":"JUKE","vin_series":"SL","vin_engine":"1.6L I-4 DI, DOHC, VVT, turbo, 188HP","vin_fuel_type":"Gasoline","vin_cylinder":"4 Cyl","vin_restraint_system":"Front Impact Airbag Driver;front Side Impact Airbag Driver;overhead Airbags;front Impact A","vin_transmission":"Automatic","vin_drive_line_type":"Front Wheel Drive","loss_type":"","primary_damage":"Normal Wear & Tear","secondary_damage":"","key_status":"Y","airbags":"INTACT","vehicle_wheels":null,"shrink_wrap":false,"videos":[{"url":"https://mediastorageaccountprod.blob.core.windows.net/media/42472392_VES-100_1","title":"Engine Video"}]},{"year":2012,"stock_number":42507360,"auction_in_progress":false,"images":["https://s3-us-west-1.amazonaws.com/vehimg/12558/42507360-1L.jpg","https://s3-us-west-1.amazonaws.com/vehimg/12558/42507360-2L.jpg","https://s3-us-west-1.amazonaws.com/vehimg/12558/42507360-3L.jpg","https://s3-us-west-1.amazonaws.com/vehimg/12558/42507360-4L.jpg","https://s3-us-west-1.amazonaws.com/vehimg/12558/42507360-5L.jpg","https://s3-us-west-1.amazonaws.com/vehimg/12558/42507360-6L.jpg","https://s3-us-west-1.amazonaws.com/vehimg/12558/42507360-7L.jpg","https://s3-us-west-1.amazonaws.com/vehimg/12558/42507360-8L.jpg","https://s3-us-west-1.amazonaws.com/vehimg/12558/42507360-9L.jpg","https://s3-us-west-1.amazonaws.com/vehimg/12558/42507360-10L.jpg","https://s3-us-west-1.amazonaws.com/vehimg/12558/42507360-11L.jpg","https://s3-us-west-1.amazonaws.com/vehimg/12558/42507360-12L.jpg","https://s3-us-west-1.amazonaws.com/vehimg/12558/42507360-13L.jpg","https://s3-us-west-1.amazonaws.com/vehimg/12558/42507360-14L.jpg","https://s3-us-west-1.amazonaws.com/vehimg/12558/42507360-15L.jpg","https://s3-us-west-1.amazonaws.com/vehimg/12558/42507360-16L.jpg"],"vehicle_name":"2012 CHEVROLET SILVERADO 1500 LT","odometer_value":193753,"odometer_type":"mi","odometer_status":"ACTUAL","location_city":"PALMETTO","location_state":"FL","location_zip":"34221","location_address":"1208 17TH ST. EAST","damage":null,"color":"Black","interior_color":"","auction_verification":"NOT SPECIFIED","start_code":"Stationary","vin":"3GCPKSE77CG128178","already_sold":false,"buy_it_now":null,"retail_value":12565,"repair_cost":11133,"body_style":"CREW CAB","current_bid_value":0,"currency":"USD","download_all_auction_pictures_url":"/rest-api/v2/lots/42507360/download-all-auction-pictures","show_clearvin_badge":true,"title_brand":"","vin_manufactured_country":"","vin_body":"Crew Cab","vin_vehicle_class":"","vin_model":"SILVERADO 1500","vin_series":"LT","vin_engine":"5.3L V-8 VVT, 315HP","vin_fuel_type":"Flexible Fuel","vin_cylinder":"8 Cyl","vin_restraint_system":"Front Impact Airbag Driver;front Side Impact Airbag Driver;overhead Airbags;front Impact A","vin_transmission":"Automatic","vin_drive_line_type":"Four Wheel Drive","loss_type":"Other","primary_damage":"","secondary_damage":"","key_status":"Y","airbags":"INTACT","vehicle_wheels":null,"shrink_wrap":false,"videos":[]},{"year":2015,"stock_number":42017527,"auction_in_progress":false,"images":["https://s3-us-west-1.amazonaws.com/vehimg/36566/42017527-1L.jpg","https://s3-us-west-1.amazonaws.com/vehimg/36566/42017527-2L.jpg","https://s3-us-west-1.amazonaws.com/vehimg/36566/42017527-3L.jpg","https://s3-us-west-1.amazonaws.com/vehimg/36566/42017527-4L.jpg","https://s3-us-west-1.amazonaws.com/vehimg/36566/42017527-5L.jpg","https://s3-us-west-1.amazonaws.com/vehimg/36566/42017527-6L.jpg","https://s3-us-west-1.amazonaws.com/vehimg/36566/42017527-7L.jpg","https://s3-us-west-1.amazonaws.com/vehimg/36566/42017527-8L.jpg","https://s3-us-west-1.amazonaws.com/vehimg/36566/42017527-9L.jpg","https://s3-us-west-1.amazonaws.com/vehimg/36566/42017527-10L.jpg","https://s3-us-west-1.amazonaws.com/vehimg/36566/42017527-11L.jpg","https://s3-us-west-1.amazonaws.com/vehimg/36566/42017527-12L.jpg","https://s3-us-west-1.amazonaws.com/vehimg/36566/42017527-13L.jpg","https://s3-us-west-1.amazonaws.com/vehimg/36566/42017527-14L.jpg","https://s3-us-west-1.amazonaws.com/vehimg/36566/42017527-15L.jpg","https://s3-us-west-1.amazonaws.com/vehimg/36566/42017527-16L.jpg"],"vehicle_name":"2015 LINCOLN MKZ","odometer_value":115507,"odometer_type":"mi","odometer_status":"NOT ACTUAL","location_city":"SOUTH BEND","location_state":"IN","location_zip":"46619","location_address":"25631 STATE ROAD 2","damage":"FRONT END","color":"Brown","interior_color":"","auction_verification":"NOT SPECIFIED","start_code":"Stationary","vin":"3LN6L2JK1FR620860","already_sold":false,"buy_it_now":975,"retail_value":13069,"repair_cost":13069,"body_style":"SEDAN","current_bid_value":0,"currency":"USD","download_all_auction_pictures_url":"/rest-api/v2/lots/42017527/download-all-auction-pictures","show_clearvin_badge":true,"title_brand":"","vin_manufactured_country":"","vin_body":"Sedan","vin_vehicle_class":"","vin_model":"MKZ","vin_series":"","vin_engine":"3.7L V-6 DOHC, VVT, 300HP","vin_fuel_type":"Other","vin_cylinder":"","vin_restraint_system":"","vin_transmission":"Unknown","vin_drive_line_type":"All Wheel Drive","loss_type":"Collision","primary_damage":"Front End","secondary_damage":"","key_status":"Y","airbags":"DEPLOYED","vehicle_wheels":null,"shrink_wrap":false,"videos":[]},{"year":2014,"stock_number":42426246,"auction_in_progress":false,"images":["https://s3-us-west-1.amazonaws.com/vehimg/25740/42426246-1L.jpg","https://s3-us-west-1.amazonaws.com/vehimg/25740/42426246-2L.jpg","https://s3-us-west-1.amazonaws.com/vehimg/25740/42426246-3L.jpg","https://s3-us-west-1.amazonaws.com/vehimg/25740/42426246-4L.jpg","https://s3-us-west-1.amazonaws.com/vehimg/25740/42426246-5L.jpg","https://s3-us-west-1.amazonaws.com/vehimg/25740/42426246-6L.jpg","https://s3-us-west-1.amazonaws.com/vehimg/25740/42426246-7L.jpg","https://s3-us-west-1.amazonaws.com/vehimg/25740/42426246-8L.jpg","https://s3-us-west-1.amazonaws.com/vehimg/25740/42426246-9L.jpg","https://s3-us-west-1.amazonaws.com/vehimg/25740/42426246-10L.jpg","https://s3-us-west-1.amazonaws.com/vehimg/25740/42426246-11L.jpg","https://s3-us-west-1.amazonaws.com/vehimg/25740/42426246-12L.jpg","https://s3-us-west-1.amazonaws.com/vehimg/25740/42426246-13L.jpg","https://s3-us-west-1.amazonaws.com/vehimg/25740/42426246-14L.jpg","https://s3-us-west-1.amazonaws.com/vehimg/25740/42426246-15L.jpg","https://s3-us-west-1.amazonaws.com/vehimg/25740/42426246-16L.jpg"],"vehicle_name":"2014 DODGE DART SXT","odometer_value":94698,"odometer_type":"mi","odometer_status":"ACTUAL","location_city":"JACKSONVILLE","location_state":"FL","location_zip":"32218","location_address":"186 PECAN PARK RD","damage":"FRONT & REAR","color":"Red","interior_color":"","auction_verification":"Run & Drive Verified","start_code":"Run & Drive","vin":"1C3CDFBB3ED671718","already_sold":false,"buy_it_now":1125,"retail_value":2325,"repair_cost":null,"body_style":"SEDAN","current_bid_value":0,"currency":"USD","download_all_auction_pictures_url":"/rest-api/v2/lots/42426246/download-all-auction-pictures","show_clearvin_badge":true,"title_brand":"","vin_manufactured_country":"","vin_body":"Sedan","vin_vehicle_class":"","vin_model":"DART","vin_series":"SXT","vin_engine":"2.4L I-4 VVT, 184HP","vin_fuel_type":"Gasoline","vin_cylinder":"4 Cyl","vin_restraint_system":"Front Impact Airbag Driver;front Side Impact Airbag Driver;overhead Airbags;front Impact A","vin_transmission":"Automatic","vin_drive_line_type":"Front Wheel Drive","loss_type":"Other","primary_damage":"Front & Rear","secondary_damage":"Left & Right Side","key_status":"Y","airbags":"INTACT","vehicle_wheels":null,"shrink_wrap":false,"videos":[{"url":"https://mediastorageaccountprod.blob.core.windows.net/media/42918813_VES-100_1","title":"Engine Video"}]},{"year":2015,"stock_number":42088567,"auction_in_progress":false,"images":["https://s3-us-west-1.amazonaws.com/vehimg/39077/42088567-1L.jpg","https://s3-us-west-1.amazonaws.com/vehimg/39077/42088567-2L.jpg","https://s3-us-west-1.amazonaws.com/vehimg/39077/42088567-3L.jpg","https://s3-us-west-1.amazonaws.com/vehimg/39077/42088567-4L.jpg","https://s3-us-west-1.amazonaws.com/vehimg/39077/42088567-5L.jpg","https://s3-us-west-1.amazonaws.com/vehimg/39077/42088567-6L.jpg","https://s3-us-west-1.amazonaws.com/vehimg/39077/42088567-7L.jpg","https://s3-us-west-1.amazonaws.com/vehimg/39077/42088567-8L.jpg","https://s3-us-west-1.amazonaws.com/vehimg/39077/42088567-9L.jpg","https://s3-us-west-1.amazonaws.com/vehimg/39077/42088567-10L.jpg","https://s3-us-west-1.amazonaws.com/vehimg/39077/42088567-11L.jpg","https://s3-us-west-1.amazonaws.com/vehimg/39077/42088567-12L.jpg","https://s3-us-west-1.amazonaws.com/vehimg/39077/42088567-13L.jpg","https://s3-us-west-1.amazonaws.com/vehimg/39077/42088567-14L.jpg","https://s3-us-west-1.amazonaws.com/vehimg/39077/42088567-15L.jpg","https://s3-us-west-1.amazonaws.com/vehimg/39077/42088567-16L.jpg","https://s3-us-west-1.amazonaws.com/vehimg/39077/42088567-17L.jpg"],"vehicle_name":"2015 HYUNDAI SONATA SPORT","odometer_value":195409,"odometer_type":"mi","odometer_status":"ACTUAL","location_city":"TURNERSVILLE","location_state":"NJ","location_zip":"08012","location_address":"250 BLACKWOOD BARNSBORO RD","damage":"FRONT END","color":"Blue","interior_color":"","auction_verification":"Run & Drive Verified","start_code":"Run & Drive","vin":"5NPE34AF0FH085313","already_sold":false,"buy_it_now":null,"retail_value":4775,"repair_cost":null,"body_style":"SEDAN","current_bid_value":0,"currency":"USD","download_all_auction_pictures_url":"/rest-api/v2/lots/42088567/download-all-auction-pictures","show_clearvin_badge":true,"title_brand":"","vin_manufactured_country":"","vin_body":"Sedan","vin_vehicle_class":"","vin_model":"SONATA","vin_series":"SPORT","vin_engine":"2.4L I-4 DI, DOHC, VVT, 185HP","vin_fuel_type":"Gasoline","vin_cylinder":"4 Cyl","vin_restraint_system":"Knee Airbag;front Side Impact Airbag Passenger;front Impact Airbag Passenger;overhead Airba","vin_transmission":"Automatic","vin_drive_line_type":"Front Wheel Drive","loss_type":"Other","primary_damage":"Front End","secondary_damage":"","key_status":"Y","airbags":"INTACT","vehicle_wheels":null,"shrink_wrap":false,"videos":[{"url":"https://mediastorageaccountprod.blob.core.windows.net/media/42580331_VES-100_1","title":"Engine Video"}]},{"year":2014,"stock_number":42550256,"auction_in_progress":false,"images":["https://s3-us-west-1.amazonaws.com/vehimg/36972/42550256-1L.jpg","https://s3-us-west-1.amazonaws.com/vehimg/36972/42550256-2L.jpg","https://s3-us-west-1.amazonaws.com/vehimg/36972/42550256-3L.jpg","https://s3-us-west-1.amazonaws.com/vehimg/36972/42550256-4L.jpg","https://s3-us-west-1.amazonaws.com/vehimg/36972/42550256-5L.jpg","https://s3-us-west-1.amazonaws.com/vehimg/36972/42550256-6L.jpg","https://s3-us-west-1.amazonaws.com/vehimg/36972/42550256-7L.jpg","https://s3-us-west-1.amazonaws.com/vehimg/36972/42550256-8L.jpg","https://s3-us-west-1.amazonaws.com/vehimg/36972/42550256-9L.jpg","https://s3-us-west-1.amazonaws.com/vehimg/36972/42550256-10L.jpg","https://s3-us-west-1.amazonaws.com/vehimg/36972/42550256-11L.jpg"],"vehicle_name":"2014 CHRYSLER TOWN & COUNTRY TOURING","odometer_value":181119,"odometer_type":"mi","odometer_status":"ACTUAL","location_city":"LORAIN","location_state":"OH","location_zip":"44053","location_address":"7437 DEER TRAIL LANE","damage":"NORMAL WEAR & TEAR","color":"Silver","interior_color":"","auction_verification":"Run & Drive Verified","start_code":"Run & Drive","vin":"2C4RC1BG4ER434241","already_sold":false,"buy_it_now":975,"retail_value":3300,"repair_cost":null,"body_style":"LWB","current_bid_value":0,"currency":"USD","download_all_auction_pictures_url":"/rest-api/v2/lots/42550256/download-all-auction-pictures","show_clearvin_badge":true,"title_brand":"","vin_manufactured_country":"","vin_body":"Lwb","vin_vehicle_class":"","vin_model":"TOWN & COUNTRY","vin_series":"TOURING","vin_engine":"3.6L V-6 DOHC, VVT, 283HP","vin_fuel_type":"Flexible Fuel","vin_cylinder":"6 Cyl","vin_restraint_system":"Front Impact Airbag Driver;front Side Impact Airbag Driver;overhead Airbags;front Impact A","vin_transmission":"Automatic","vin_drive_line_type":"Front Wheel Drive","loss_type":"","primary_damage":"Normal Wear & Tear","secondary_damage":"","key_status":"Y","airbags":"INTACT","vehicle_wheels":null,"shrink_wrap":false,"videos":[{"url":"https://mediastorageaccountprod.blob.core.windows.net/media/43043105_VES-100_1","title":"Engine Video"}]},{"year":2014,"stock_number":42145670,"auction_in_progress":false,"images":["https://s3-us-west-1.amazonaws.com/vehimg/24340/42145670-1L.jpg","https://s3-us-west-1.amazonaws.com/vehimg/24340/42145670-2L.jpg","https://s3-us-west-1.amazonaws.com/vehimg/24340/42145670-3L.jpg","https://s3-us-west-1.amazonaws.com/vehimg/24340/42145670-4L.jpg","https://s3-us-west-1.amazonaws.com/vehimg/24340/42145670-5L.jpg","https://s3-us-west-1.amazonaws.com/vehimg/24340/42145670-6L.jpg","https://s3-us-west-1.amazonaws.com/vehimg/24340/42145670-7L.jpg","https://s3-us-west-1.amazonaws.com/vehimg/24340/42145670-8L.jpg","https://s3-us-west-1.amazonaws.com/vehimg/24340/42145670-9L.jpg","https://s3-us-west-1.amazonaws.com/vehimg/24340/42145670-10L.jpg","https://s3-us-west-1.amazonaws.com/vehimg/24340/42145670-11L.jpg","https://s3-us-west-1.amazonaws.com/vehimg/24340/42145670-12L.jpg","https://s3-us-west-1.amazonaws.com/vehimg/24340/42145670-13L.jpg","https://s3-us-west-1.amazonaws.com/vehimg/24340/42145670-14L.jpg","https://s3-us-west-1.amazonaws.com/vehimg/24340/42145670-15L.jpg","https://s3-us-west-1.amazonaws.com/vehimg/24340/42145670-16L.jpg","https://s3-us-west-1.amazonaws.com/vehimg/24340/42145670-17L.jpg"],"vehicle_name":"2014 FORD MUSTANG V6 PREMIUM","odometer_value":77466,"odometer_type":"mi","odometer_status":"ACTUAL","location_city":"GIBSONIA","location_state":"PA","location_zip":"15044","location_address":"49 BAIRDFORD RD","damage":"FRONT END","color":"Red","interior_color":"","auction_verification":"Run & Drive Verified","start_code":"Run & Drive","vin":"1ZVBP8AM3E5271971","already_sold":false,"buy_it_now":1450,"retail_value":11866,"repair_cost":11440,"body_style":"COUPE","current_bid_value":0,"currency":"USD","download_all_auction_pictures_url":"/rest-api/v2/lots/42145670/download-all-auction-pictures","show_clearvin_badge":true,"title_brand":"","vin_manufactured_country":"","vin_body":"Coupe 2 Door","vin_vehicle_class":"","vin_model":"MUSTANG","vin_series":"","vin_engine":"3.7L V6 FI DOHC 24V NF4","vin_fuel_type":"Gasoline","vin_cylinder":"6 Cyl","vin_restraint_system":"Dual Air Bags Front And Sides/active Belts","vin_transmission":"Unknown","vin_drive_line_type":"Rear Wheel Drive","loss_type":"Collision","primary_damage":"Front End","secondary_damage":"Left & Right Side","key_status":"Y","airbags":"DEPLOYED","vehicle_wheels":null,"shrink_wrap":false,"videos":[{"url":"https://mediastorageaccountprod.blob.core.windows.net/media/42637558_VES-100_1","title":"Engine Video"}]},{"year":2012,"stock_number":42165893,"auction_in_progress":false,"images":["https://s3-us-west-1.amazonaws.com/vehimg/38718/42165893-1L.jpg","https://s3-us-west-1.amazonaws.com/vehimg/38718/42165893-2L.jpg","https://s3-us-west-1.amazonaws.com/vehimg/38718/42165893-3L.jpg","https://s3-us-west-1.amazonaws.com/vehimg/38718/42165893-4L.jpg","https://s3-us-west-1.amazonaws.com/vehimg/38718/42165893-5L.jpg","https://s3-us-west-1.amazonaws.com/vehimg/38718/42165893-6L.jpg","https://s3-us-west-1.amazonaws.com/vehimg/38718/42165893-7L.jpg","https://s3-us-west-1.amazonaws.com/vehimg/38718/42165893-8L.jpg","https://s3-us-west-1.amazonaws.com/vehimg/38718/42165893-9L.jpg","https://s3-us-west-1.amazonaws.com/vehimg/38718/42165893-10L.jpg","https://s3-us-west-1.amazonaws.com/vehimg/38718/42165893-11L.jpg","https://s3-us-west-1.amazonaws.com/vehimg/38718/42165893-12L.jpg"],"vehicle_name":"2012 NISSAN ALTIMA 2.5 S","odometer_value":198843,"odometer_type":"mi","odometer_status":"ACTUAL","location_city":"MEDFORD","location_state":"NY","location_zip":"11763","location_address":"66 PECONIC AVE","damage":"FRONT END","color":"Black","interior_color":"","auction_verification":"NOT SPECIFIED","start_code":"Stationary","vin":"1N4AL2AP1CC157919","already_sold":false,"buy_it_now":null,"retail_value":1875,"repair_cost":null,"body_style":"SEDAN","current_bid_value":0,"currency":"USD","download_all_auction_pictures_url":"/rest-api/v2/lots/42165893/download-all-auction-pictures","show_clearvin_badge":true,"title_brand":"","vin_manufactured_country":"","vin_body":"Sedan","vin_vehicle_class":"","vin_model":"ALTIMA","vin_series":"2.5 S","vin_engine":"2.5L I-4 DOHC, VVT, 170HP","vin_fuel_type":"Gasoline","vin_cylinder":"4 Cyl","vin_restraint_system":"Front Side Impact Airbag Passenger;front Impact Airbag Passenger;overhead Airbags;front Sid","vin_transmission":"Automatic","vin_drive_line_type":"Front Wheel Drive","loss_type":"Collision","primary_damage":"Front End","secondary_damage":"Left & Right Side","key_status":"Y","airbags":"DEPLOYED","vehicle_wheels":null,"shrink_wrap":false,"videos":[]},{"year":2013,"stock_number":42531647,"auction_in_progress":false,"images":["https://s3-us-west-1.amazonaws.com/vehimg/21900/42531647-1L.jpg","https://s3-us-west-1.amazonaws.com/vehimg/21900/42531647-2L.jpg","https://s3-us-west-1.amazonaws.com/vehimg/21900/42531647-3L.jpg","https://s3-us-west-1.amazonaws.com/vehimg/21900/42531647-4L.jpg","https://s3-us-west-1.amazonaws.com/vehimg/21900/42531647-5L.jpg","https://s3-us-west-1.amazonaws.com/vehimg/21900/42531647-6L.jpg","https://s3-us-west-1.amazonaws.com/vehimg/21900/42531647-7L.jpg","https://s3-us-west-1.amazonaws.com/vehimg/21900/42531647-8L.jpg","https://s3-us-west-1.amazonaws.com/vehimg/21900/42531647-9L.jpg","https://s3-us-west-1.amazonaws.com/vehimg/21900/42531647-10L.jpg","https://s3-us-west-1.amazonaws.com/vehimg/21900/42531647-11L.jpg","https://s3-us-west-1.amazonaws.com/vehimg/21900/42531647-12L.jpg","https://s3-us-west-1.amazonaws.com/vehimg/21900/42531647-13L.jpg","https://s3-us-west-1.amazonaws.com/vehimg/21900/42531647-14L.jpg","https://s3-us-west-1.amazonaws.com/vehimg/21900/42531647-15L.jpg","https://s3-us-west-1.amazonaws.com/vehimg/21900/42531647-16L.jpg","https://s3-us-west-1.amazonaws.com/vehimg/21900/42531647-17L.jpg"],"vehicle_name":"2013 TOYOTA PRIUS C THREE","odometer_value":158228,"odometer_type":"mi","odometer_status":"ACTUAL","location_city":"CULPEPER","location_state":"VA","location_zip":"22701","location_address":"15201 REVIEW RD","damage":"FRONT END","color":"Gray","interior_color":"","auction_verification":"Run & Drive Verified","start_code":"Run & Drive","vin":"JTDKDTB31D1046894","already_sold":false,"buy_it_now":null,"retail_value":8786,"repair_cost":8786,"body_style":"HATCHBACK","current_bid_value":0,"currency":"USD","download_all_auction_pictures_url":"/rest-api/v2/lots/42531647/download-all-auction-pictures","show_clearvin_badge":true,"title_brand":"","vin_manufactured_country":"","vin_body":"Hatchback","vin_vehicle_class":"","vin_model":"PRIUS C","vin_series":"THREE","vin_engine":"1.5L I-4 DOHC, VVT, 73HP","vin_fuel_type":"Hybrid","vin_cylinder":"4 Cyl","vin_restraint_system":"Front Impact Airbag Driver;front Side Impact Airbag Driver;overhead Airbags;front Impact A","vin_transmission":"Automatic","vin_drive_line_type":"Front Wheel Drive","loss_type":"Collision","primary_damage":"Front End","secondary_damage":"Roof","key_status":"Y","airbags":"INTACT","vehicle_wheels":null,"shrink_wrap":false,"videos":[{"url":"https://mediastorageaccountprod.blob.core.windows.net/media/43024455_VES-100_1","title":"Engine Video"}]},{"year":2014,"stock_number":39197999,"auction_in_progress":false,"images":["https://s3-us-west-1.amazonaws.com/vehimg/65925/39197999-1L.jpg","https://s3-us-west-1.amazonaws.com/vehimg/65925/39197999-2L.jpg","https://s3-us-west-1.amazonaws.com/vehimg/65925/39197999-3L.jpg","https://s3-us-west-1.amazonaws.com/vehimg/65925/39197999-4L.jpg","https://s3-us-west-1.amazonaws.com/vehimg/65925/39197999-5L.jpg","https://s3-us-west-1.amazonaws.com/vehimg/65925/39197999-6L.jpg","https://s3-us-west-1.amazonaws.com/vehimg/65925/39197999-7L.jpg","https://s3-us-west-1.amazonaws.com/vehimg/65925/39197999-8L.jpg","https://s3-us-west-1.amazonaws.com/vehimg/65925/39197999-9L.jpg","https://s3-us-west-1.amazonaws.com/vehimg/65925/39197999-10L.jpg","https://s3-us-west-1.amazonaws.com/vehimg/65925/39197999-11L.jpg","https://s3-us-west-1.amazonaws.com/vehimg/65925/39197999-12L.jpg","https://s3-us-west-1.amazonaws.com/vehimg/65925/39197999-13L.jpg","https://s3-us-west-1.amazonaws.com/vehimg/65925/39197999-14L.jpg","https://s3-us-west-1.amazonaws.com/vehimg/65925/39197999-15L.jpg","https://s3-us-west-1.amazonaws.com/vehimg/65925/39197999-16L.jpg","https://s3-us-west-1.amazonaws.com/vehimg/65925/39197999-17L.jpg","https://s3-us-west-1.amazonaws.com/vehimg/65925/39197999-18L.jpg"],"vehicle_name":"2014 MERCEDES-BENZ E 350 4MATIC","odometer_value":96107,"odometer_type":"mi","odometer_status":"ACTUAL","location_city":"MEDFORD","location_state":"NY","location_zip":"11763","location_address":"66 PECONIC AVE","damage":"FRONT END","color":"White","interior_color":"Black","auction_verification":"NOT SPECIFIED","start_code":"Starts","vin":"WDDHF8JB5EB022531","already_sold":false,"buy_it_now":null,"retail_value":13981,"repair_cost":null,"body_style":"SEDAN","current_bid_value":0,"currency":"USD","download_all_auction_pictures_url":"/rest-api/v2/lots/39197999/download-all-auction-pictures","show_clearvin_badge":true,"title_brand":"","vin_manufactured_country":null,"vin_body":"Sedan","vin_vehicle_class":null,"vin_model":"E 350","vin_series":"4MATIC","vin_engine":"3.5L V-6 DI, DOHC, VVT, 302HP","vin_fuel_type":"Gasoline","vin_cylinder":"6 Cyl","vin_restraint_system":"Front Impact Airbag Driver;front Side Impact Airbag Driver;overhead Airbags;front Impact A","vin_transmission":"Automatic","vin_drive_line_type":"All Wheel Drive","loss_type":"Collision","primary_damage":"Front End","secondary_damage":"","key_status":"Y","airbags":"INTACT","vehicle_wheels":null,"shrink_wrap":false,"videos":[]},{"year":2015,"stock_number":42348897,"auction_in_progress":false,"images":["https://s3-us-west-1.amazonaws.com/vehimg/61709/42348897-1L.jpg","https://s3-us-west-1.amazonaws.com/vehimg/61709/42348897-2L.jpg","https://s3-us-west-1.amazonaws.com/vehimg/61709/42348897-3L.jpg","https://s3-us-west-1.amazonaws.com/vehimg/61709/42348897-4L.jpg","https://s3-us-west-1.amazonaws.com/vehimg/61709/42348897-5L.jpg","https://s3-us-west-1.amazonaws.com/vehimg/61709/42348897-6L.jpg","https://s3-us-west-1.amazonaws.com/vehimg/61709/42348897-7L.jpg","https://s3-us-west-1.amazonaws.com/vehimg/61709/42348897-8L.jpg","https://s3-us-west-1.amazonaws.com/vehimg/61709/42348897-9L.jpg","https://s3-us-west-1.amazonaws.com/vehimg/61709/42348897-10L.jpg","https://s3-us-west-1.amazonaws.com/vehimg/61709/42348897-11L.jpg","https://s3-us-west-1.amazonaws.com/vehimg/61709/42348897-12L.jpg","https://s3-us-west-1.amazonaws.com/vehimg/61709/42348897-13L.jpg","https://s3-us-west-1.amazonaws.com/vehimg/61709/42348897-14L.jpg","https://s3-us-west-1.amazonaws.com/vehimg/61709/42348897-15L.jpg","https://s3-us-west-1.amazonaws.com/vehimg/61709/42348897-16L.jpg"],"vehicle_name":"2015 TOYOTA CAMRY LE/SE/XLE/XSE","odometer_value":93050,"odometer_type":"mi","odometer_status":"ACTUAL","location_city":"MEDFORD","location_state":"NY","location_zip":"11763","location_address":"66 PECONIC AVE","damage":"FRONT & REAR","color":"Gray","interior_color":"Black","auction_verification":"Run & Drive Verified","start_code":"Run & Drive","vin":"4T1BF1FK1FU954887","already_sold":false,"buy_it_now":null,"retail_value":11645,"repair_cost":null,"body_style":"SEDAN","current_bid_value":0,"currency":"USD","download_all_auction_pictures_url":"/rest-api/v2/lots/42348897/download-all-auction-pictures","show_clearvin_badge":true,"title_brand":"","vin_manufactured_country":"","vin_body":"Sedan","vin_vehicle_class":"","vin_model":"CAMRY","vin_series":"LE/SE/XLE/XSE","vin_engine":"2.5L I-4 DOHC, VVT, 178HP","vin_fuel_type":"Gasoline","vin_cylinder":"4 Cyl","vin_restraint_system":"Front Impact Airbag Driver;front Side Impact Airbag Driver;overhead Airbags;front Impact A","vin_transmission":"Automatic","vin_drive_line_type":"Front Wheel Drive","loss_type":"Collision","primary_damage":"Front & Rear","secondary_damage":"Left & Right Side","key_status":"Y","airbags":"DEPLOYED","vehicle_wheels":null,"shrink_wrap":false,"videos":[{"url":"https://mediastorageaccountprod.blob.core.windows.net/media/42841156_VES-100_1","title":"Engine Video"}]},{"year":2013,"stock_number":42580797,"auction_in_progress":false,"images":["https://s3-us-west-1.amazonaws.com/vehimg/41865/42580797-1L.jpg","https://s3-us-west-1.amazonaws.com/vehimg/41865/42580797-2L.jpg","https://s3-us-west-1.amazonaws.com/vehimg/41865/42580797-3L.jpg","https://s3-us-west-1.amazonaws.com/vehimg/41865/42580797-4L.jpg","https://s3-us-west-1.amazonaws.com/vehimg/41865/42580797-5L.jpg","https://s3-us-west-1.amazonaws.com/vehimg/41865/42580797-6L.jpg","https://s3-us-west-1.amazonaws.com/vehimg/41865/42580797-7L.jpg","https://s3-us-west-1.amazonaws.com/vehimg/41865/42580797-8L.jpg","https://s3-us-west-1.amazonaws.com/vehimg/41865/42580797-9L.jpg","https://s3-us-west-1.amazonaws.com/vehimg/41865/42580797-10L.jpg","https://s3-us-west-1.amazonaws.com/vehimg/41865/42580797-11L.jpg"],"vehicle_name":"2013 NISSAN ROGUE SV","odometer_value":137611,"odometer_type":"mi","odometer_status":"ACTUAL","location_city":"SUFFOLK","location_state":"VA","location_zip":"23434","location_address":"1389 PORTSMOUTH BLVD.","damage":"REAR","color":"Black","interior_color":"","auction_verification":"Run & Drive Verified","start_code":"Run & Drive","vin":"JN8AS5MT8DW034548","already_sold":false,"buy_it_now":975,"retail_value":2175,"repair_cost":null,"body_style":"UTILITY","current_bid_value":0,"currency":"USD","download_all_auction_pictures_url":"/rest-api/v2/lots/42580797/download-all-auction-pictures","show_clearvin_badge":true,"title_brand":"","vin_manufactured_country":"","vin_body":"Utility","vin_vehicle_class":"","vin_model":"ROGUE","vin_series":"SV","vin_engine":"2.5L I-4 DOHC, VVT, 170HP","vin_fuel_type":"Gasoline","vin_cylinder":"4 Cyl","vin_restraint_system":"Front Impact Airbag Driver;front Side Impact Airbag Driver;overhead Airbags;front Impact A","vin_transmission":"Automatic","vin_drive_line_type":"Front Wheel Drive","loss_type":"Other","primary_damage":"Rear","secondary_damage":"Left Rear","key_status":"Y","airbags":"INTACT","vehicle_wheels":null,"shrink_wrap":false,"videos":[{"url":"https://mediastorageaccountprod.blob.core.windows.net/media/43073710_VES-100_1","title":"Engine Video"}]},{"year":2013,"stock_number":42321556,"auction_in_progress":false,"images":["https://s3-us-west-1.amazonaws.com/vehimg/99239/42321556-1L.jpg","https://s3-us-west-1.amazonaws.com/vehimg/99239/42321556-2L.jpg","https://s3-us-west-1.amazonaws.com/vehimg/99239/42321556-3L.jpg","https://s3-us-west-1.amazonaws.com/vehimg/99239/42321556-4L.jpg","https://s3-us-west-1.amazonaws.com/vehimg/99239/42321556-5L.jpg","https://s3-us-west-1.amazonaws.com/vehimg/99239/42321556-6L.jpg","https://s3-us-west-1.amazonaws.com/vehimg/99239/42321556-7L.jpg","https://s3-us-west-1.amazonaws.com/vehimg/99239/42321556-8L.jpg","https://s3-us-west-1.amazonaws.com/vehimg/99239/42321556-9L.jpg","https://s3-us-west-1.amazonaws.com/vehimg/99239/42321556-10L.jpg","https://s3-us-west-1.amazonaws.com/vehimg/99239/42321556-11L.jpg"],"vehicle_name":"2013 VOLKSWAGEN JETTA 2.5L SE","odometer_value":160717,"odometer_type":"mi","odometer_status":"ACTUAL","location_city":"ACWORTH","location_state":"GA","location_zip":"30101","location_address":"6242 BLACKACRE TRAIL","damage":"FRONT END","color":"Yellow","interior_color":"","auction_verification":"NOT SPECIFIED","start_code":"Stationary","vin":"3VWDP7AJ9DM395244","already_sold":false,"buy_it_now":null,"retail_value":4530,"repair_cost":null,"body_style":"SEDAN","current_bid_value":0,"currency":"USD","download_all_auction_pictures_url":"/rest-api/v2/lots/42321556/download-all-auction-pictures","show_clearvin_badge":true,"title_brand":"","vin_manufactured_country":"","vin_body":"Sedan","vin_vehicle_class":"","vin_model":"JETTA","vin_series":"2.5L SE","vin_engine":"2.5L I-5 DOHC, VVT, 170HP","vin_fuel_type":"Gasoline","vin_cylinder":"5 Cyl","vin_restraint_system":"Front Impact Airbag Driver;front Side Impact Airbag Driver;overhead Airbags;front Impact A","vin_transmission":"Automatic","vin_drive_line_type":"Front Wheel Drive","loss_type":"Collision","primary_damage":"Front End","secondary_damage":"Left & Right Side","key_status":"Y","airbags":"DEPLOYED","vehicle_wheels":null,"shrink_wrap":false,"videos":[]},{"year":2013,"stock_number":42013958,"auction_in_progress":false,"images":["https://s3-us-west-1.amazonaws.com/vehimg/21551/42013958-1L.jpg","https://s3-us-west-1.amazonaws.com/vehimg/21551/42013958-2L.jpg","https://s3-us-west-1.amazonaws.com/vehimg/21551/42013958-3L.jpg","https://s3-us-west-1.amazonaws.com/vehimg/21551/42013958-4L.jpg","https://s3-us-west-1.amazonaws.com/vehimg/21551/42013958-5L.jpg","https://s3-us-west-1.amazonaws.com/vehimg/21551/42013958-6L.jpg","https://s3-us-west-1.amazonaws.com/vehimg/21551/42013958-7L.jpg","https://s3-us-west-1.amazonaws.com/vehimg/21551/42013958-8L.jpg","https://s3-us-west-1.amazonaws.com/vehimg/21551/42013958-9L.jpg","https://s3-us-west-1.amazonaws.com/vehimg/21551/42013958-10L.jpg","https://s3-us-west-1.amazonaws.com/vehimg/21551/42013958-11L.jpg","https://s3-us-west-1.amazonaws.com/vehimg/21551/42013958-12L.jpg","https://s3-us-west-1.amazonaws.com/vehimg/21551/42013958-13L.jpg","https://s3-us-west-1.amazonaws.com/vehimg/21551/42013958-14L.jpg","https://s3-us-west-1.amazonaws.com/vehimg/21551/42013958-15L.jpg","https://s3-us-west-1.amazonaws.com/vehimg/21551/42013958-16L.jpg"],"vehicle_name":"2013 CHEVROLET CRUZE LS AUTO","odometer_value":133481,"odometer_type":"mi","odometer_status":"ACTUAL","location_city":"FLINT","location_state":"MI","location_zip":"48507","location_address":"3088 S. DYE RD","damage":"RIGHT SIDE","color":"Silver","interior_color":"","auction_verification":"NOT SPECIFIED","start_code":"Stationary","vin":"1G1PA5SG6D7105442","already_sold":false,"buy_it_now":null,"retail_value":4918,"repair_cost":4918,"body_style":"SEDAN","current_bid_value":0,"currency":"USD","download_all_auction_pictures_url":"/rest-api/v2/lots/42013958/download-all-auction-pictures","show_clearvin_badge":true,"title_brand":"","vin_manufactured_country":"","vin_body":"Sedan","vin_vehicle_class":"","vin_model":"CRUZE","vin_series":"LS AUTO","vin_engine":"1.8L I-4 DOHC, VVT, 138HP","vin_fuel_type":"Other","vin_cylinder":"","vin_restraint_system":"","vin_transmission":"Unknown","vin_drive_line_type":"Front Wheel Drive","loss_type":"Collision","primary_damage":"Right Side","secondary_damage":"","key_status":"Y","airbags":"DEPLOYED","vehicle_wheels":null,"shrink_wrap":false,"videos":[]},{"year":2013,"stock_number":42350884,"auction_in_progress":false,"images":["https://s3-us-west-1.amazonaws.com/vehimg/15444/42350884-1L.jpg","https://s3-us-west-1.amazonaws.com/vehimg/15444/42350884-2L.jpg","https://s3-us-west-1.amazonaws.com/vehimg/15444/42350884-3L.jpg","https://s3-us-west-1.amazonaws.com/vehimg/15444/42350884-4L.jpg","https://s3-us-west-1.amazonaws.com/vehimg/15444/42350884-5L.jpg","https://s3-us-west-1.amazonaws.com/vehimg/15444/42350884-6L.jpg","https://s3-us-west-1.amazonaws.com/vehimg/15444/42350884-7L.jpg","https://s3-us-west-1.amazonaws.com/vehimg/15444/42350884-8L.jpg","https://s3-us-west-1.amazonaws.com/vehimg/15444/42350884-9L.jpg","https://s3-us-west-1.amazonaws.com/vehimg/15444/42350884-10L.jpg","https://s3-us-west-1.amazonaws.com/vehimg/15444/42350884-11L.jpg","https://s3-us-west-1.amazonaws.com/vehimg/15444/42350884-12L.jpg","https://s3-us-west-1.amazonaws.com/vehimg/15444/42350884-13L.jpg","https://s3-us-west-1.amazonaws.com/vehimg/15444/42350884-14L.jpg","https://s3-us-west-1.amazonaws.com/vehimg/15444/42350884-15L.jpg"],"vehicle_name":"2013 HYUNDAI ELANTRA GLS","odometer_value":144598,"odometer_type":"mi","odometer_status":"ACTUAL","location_city":"STATEN ISLAND","location_state":"NY","location_zip":"10314","location_address":"1900 INDUSTRY ROAD","damage":"THEFT","color":"Gray","interior_color":"","auction_verification":"Run & Drive Verified","start_code":"Run & Drive","vin":"5NPDH4AE2DH286311","already_sold":false,"buy_it_now":null,"retail_value":4163,"repair_cost":4316,"body_style":"SEDAN","current_bid_value":0,"currency":"USD","download_all_auction_pictures_url":"/rest-api/v2/lots/42350884/download-all-auction-pictures","show_clearvin_badge":true,"title_brand":"","vin_manufactured_country":"","vin_body":"Sedan 4 Door","vin_vehicle_class":"","vin_model":"ELANTRA","vin_series":"GLS/LIMITED","vin_engine":"1.8L I4 FI DOHC 16V NF4","vin_fuel_type":"Gasoline","vin_cylinder":"4 Cyl","vin_restraint_system":"Du Frnt/sd/hd Air Bgs/rr Hd Ar Bgs/act Belts","vin_transmission":"Unknown","vin_drive_line_type":"Front Wheel Drive","loss_type":"Theft","primary_damage":"Theft","secondary_damage":"Left Front","key_status":"Y","airbags":"INTACT","vehicle_wheels":null,"shrink_wrap":false,"videos":[]},{"year":2013,"stock_number":42585675,"auction_in_progress":false,"images":["https://s3-us-west-1.amazonaws.com/vehimg/32060/42585675-1L.jpg","https://s3-us-west-1.amazonaws.com/vehimg/32060/42585675-2L.jpg","https://s3-us-west-1.amazonaws.com/vehimg/32060/42585675-3L.jpg","https://s3-us-west-1.amazonaws.com/vehimg/32060/42585675-4L.jpg","https://s3-us-west-1.amazonaws.com/vehimg/32060/42585675-5L.jpg","https://s3-us-west-1.amazonaws.com/vehimg/32060/42585675-6L.jpg","https://s3-us-west-1.amazonaws.com/vehimg/32060/42585675-7L.jpg","https://s3-us-west-1.amazonaws.com/vehimg/32060/42585675-8L.jpg","https://s3-us-west-1.amazonaws.com/vehimg/32060/42585675-9L.jpg","https://s3-us-west-1.amazonaws.com/vehimg/32060/42585675-10L.jpg","https://s3-us-west-1.amazonaws.com/vehimg/32060/42585675-11L.jpg","https://s3-us-west-1.amazonaws.com/vehimg/32060/42585675-12L.jpg","https://s3-us-west-1.amazonaws.com/vehimg/32060/42585675-13L.jpg","https://s3-us-west-1.amazonaws.com/vehimg/32060/42585675-14L.jpg","https://s3-us-west-1.amazonaws.com/vehimg/32060/42585675-15L.jpg","https://s3-us-west-1.amazonaws.com/vehimg/32060/42585675-16L.jpg"],"vehicle_name":"2013 SUBARU IMPREZA 2.0I","odometer_value":147257,"odometer_type":"mi","odometer_status":"ACTUAL","location_city":"TURNERSVILLE","location_state":"NJ","location_zip":"08012","location_address":"250 BLACKWOOD BARNSBORO RD","damage":"FRONT END","color":"Blue","interior_color":"","auction_verification":"Run & Drive Verified","start_code":"Run & Drive","vin":"JF1GJAA62DH010157","already_sold":false,"buy_it_now":null,"retail_value":null,"repair_cost":null,"body_style":"SEDAN","current_bid_value":0,"currency":"USD","download_all_auction_pictures_url":"/rest-api/v2/lots/42585675/download-all-auction-pictures","show_clearvin_badge":true,"title_brand":"","vin_manufactured_country":"","vin_body":"Sedan","vin_vehicle_class":"","vin_model":"IMPREZA","vin_series":"2.0I","vin_engine":"2.0L H-4 DOHC, VVT, 148HP","vin_fuel_type":"Gasoline","vin_cylinder":"4 Cyl","vin_restraint_system":"Front Impact Airbag Driver;front Side Impact Airbag Driver;overhead Airbags;front Impact A","vin_transmission":"Automatic","vin_drive_line_type":"All Wheel Drive","loss_type":"Other","primary_damage":"Front End","secondary_damage":"Left & Right Side","key_status":"Y","airbags":"INTACT","vehicle_wheels":null,"shrink_wrap":false,"videos":[{"url":"https://mediastorageaccountprod.blob.core.windows.net/media/43078587_VES-100_1","title":"Engine Video"}]}]